{
  "packetVersion": "passive-observation-window-redacted-evidence-v0.26.1",
  "boundedPacketSha256": "17f8241642df4ba60486dd439848c58ff3f15297bed2191be1b9dfef8f5e8724",
  "redactedPreviews": [
    {
      "id": "window-evidence-1",
      "text": "Alpha research note records stable local adapter observations.",
      "rawPersisted": false,
      "policyDecision": null
    },
    {
      "id": "window-evidence-2",
      "text": "Bounded source windows produce compact redacted evidence.",
      "rawPersisted": false,
      "policyDecision": null
    },
    {
      "id": "window-evidence-3",
      "text": "Beta research note records independent multisource context.",
      "rawPersisted": false,
      "policyDecision": null
    }
  ],
  "rawSourceCache": "excluded",
  "rawPersisted": false,
  "policyDecision": null
}
