{
  "artifact": "T-synaptic-mesh-live-adapter-shadow-read-reviewer-package-v0.19.5",
  "timestamp": "2026-05-15T12:05:00.000Z",
  "summary": {
    "liveAdapterShadowReadBarrierCrossed": true,
    "localAdapterShadowReadGate": true,
    "disabledManualOperatorRunLocalPassiveReadOnly": true,
    "oneShot": true,
    "constrainedLocalReadAdapter": true,
    "singleExplicitLocalSourceOnly": true,
    "realLocalSourceRequired": true,
    "boundedWindowAndRecords": true,
    "recordLimit": 6,
    "recordsRead": 6,
    "redactedRecordsPersisted": 6,
    "humanReadableReport": true,
    "rawPersisted": false,
    "rawOutput": false,
    "agentConsumedOutput": false,
    "policyDecision": null,
    "unexpectedPermits": 0,
    "externalEffects": false,
    "enforcement": false,
    "authorization": false,
    "approvalBlockAllow": false,
    "toolExecution": false,
    "memoryConfigWrite": false,
    "watcherDaemon": false,
    "autonomousLiveMode": false,
    "networkResourceFetch": false,
    "batchMode": false,
    "phaseClosed": true,
    "usefulnessScorecardPass": true,
    "twoIndependentLocalReviews": true,
    "notGitHubUiReviews": true,
    "notDeploymentApproval": true
  },
  "packet": {
    "artifact": "T-synaptic-mesh-live-adapter-shadow-read-v0.19.5",
    "schemaVersion": "live-adapter-shadow-read-v0.19.1",
    "releaseLayer": "v0.19.5",
    "timestamp": "2026-05-15T12:05:00.000Z",
    "summary": {
      "liveAdapterShadowReadBarrierCrossed": true,
      "localAdapterShadowReadGate": true,
      "disabledManualOperatorRunLocalPassiveReadOnly": true,
      "oneShot": true,
      "constrainedLocalReadAdapter": true,
      "singleExplicitLocalSourceOnly": true,
      "realLocalSourceRequired": true,
      "boundedWindowAndRecords": true,
      "recordLimit": 6,
      "recordsRead": 6,
      "redactedRecordsPersisted": 6,
      "humanReadableReport": true,
      "rawPersisted": false,
      "rawOutput": false,
      "agentConsumedOutput": false,
      "policyDecision": null,
      "unexpectedPermits": 0,
      "externalEffects": false,
      "enforcement": false,
      "authorization": false,
      "approvalBlockAllow": false,
      "toolExecution": false,
      "memoryConfigWrite": false,
      "watcherDaemon": false,
      "autonomousLiveMode": false,
      "networkResourceFetch": false,
      "batchMode": false
    },
    "protocol": {
      "releaseLayer": "v0.19.0-alpha",
      "barrierCrossed": "local_adapter_shadow_read_gate",
      "disabledByDefault": true,
      "humanStartedManualOnly": true,
      "operatorRun": true,
      "operatorReviewRequired": true,
      "localOnly": true,
      "passiveOnly": true,
      "readOnly": true,
      "oneShot": true,
      "constrainedLocalReadAdapter": true,
      "singleExplicitLocalSourceOnly": true,
      "boundedWindowAndRecords": true,
      "maxRecords": 12,
      "realLocalSourceRequired": true,
      "fixturePositiveInputAllowed": false,
      "networkFetch": false,
      "resourceFetch": false,
      "autonomousLiveMode": false,
      "watcherDaemon": false,
      "batchMode": false,
      "toolExecution": false,
      "memoryConfigWrites": false,
      "rawPersisted": false,
      "rawOutput": false,
      "agentConsumedOutput": false,
      "machineReadablePolicyDecision": false,
      "policyDecision": null,
      "approvalBlockAllowAuthorizationEnforcement": false,
      "externalEffects": false
    },
    "adapter": {
      "id": "repo-local-file-read-adapter-v0",
      "kind": "constrained_local_read_adapter",
      "localOnly": true,
      "passiveOnly": true,
      "readOnly": true,
      "rawAdapterOutputPersisted": false
    },
    "source": {
      "kind": "explicit_repo_local_file_via_adapter",
      "repoRelativePathSha256": "b335630551682c19a781afebcf4d07bf978fb1f8ac04c6bf87428ed5106870f5",
      "absolutePathSha256": "543c81f89743c5b0f48fa0200abe84d28dd1fdb1b6687cf610469e9e998e93e0",
      "sourceSize": 2184,
      "sourceMtimeMs": null,
      "rawSourcePathPersisted": false
    },
    "retention": {
      "redactedEvidenceJsonAndHumanReportOnly": true,
      "rawPersisted": false,
      "privatePatternDetected": false,
      "decisionVerbDetected": false,
      "semanticDecisionTokenPersisted": false
    },
    "usefulnessScorecard": {
      "crossedLocalAdapterShadowReadBarrier": true,
      "usedConstrainedLocalReadAdapter": true,
      "usedRealRepoLocalSource": true,
      "notFixturePositiveInput": true,
      "boundedNRecords": true,
      "redactedHumanReadableEvidence": true,
      "readinessTheaterAvoided": true,
      "suitableNextStep": "v0.20_candidate_adapter_shadow_read_observed_failure_modes_without_authority"
    },
    "redactedRecords": [
      {
        "index": 0,
        "rawSha256": "69d94475ec9341faa582399a96139ed0a9753e5561343638b9d7543f22d8f9e4",
        "rawBytes": 23,
        "redactedSha256": "69d94475ec9341faa582399a96139ed0a9753e5561343638b9d7543f22d8f9e4",
        "redactedText": "# Synaptic Mesh v0.26.5",
        "privatePatternDetected": false,
        "decisionVerbDetected": false,
        "semanticDecisionTokenPersisted": false
      },
      {
        "index": 1,
        "rawSha256": "81118f2f2c767475a80608be0be3ccfa927335dcded66d060d110178cee1b200",
        "rawBytes": 196,
        "redactedSha256": "81118f2f2c767475a80608be0be3ccfa927335dcded66d060d110178cee1b200",
        "redactedText": "This is the public review release `v0.26.5`. Current v0.26.5 status is narrower than live runtime and crosses the next safe barrier after the v0.25 value scorecard: **passive observation window**.",
        "privatePatternDetected": false,
        "decisionVerbDetected": false,
        "semanticDecisionTokenPersisted": false
      },
      {
        "index": 2,
        "rawSha256": "2d970a7c90678796cc33de91ee8549ee03e74741de0fd0e595ffe4e464d3cb78",
        "rawBytes": 327,
        "redactedSha256": "2d970a7c90678796cc33de91ee8549ee03e74741de0fd0e595ffe4e464d3cb78",
        "redactedText": "The v0.26 ladder is disabled-by-default, operator-run one-shot, local-only, passive/read-only, bounded to explicit repo-local sources and 3 queue/outcome items, local manual outcome fixtures only, redaction-before-persist, redacted evidence",
        "privatePatternDetected": false,
        "decisionVerbDetected": false,
        "semanticDecisionTokenPersisted": false
      },
      {
        "index": 3,
        "rawSha256": "069b2439832c5843d72a813fa9c2ade9149e30982fe617d05e6214356e7c6d4a",
        "rawBytes": 296,
        "redactedSha256": "069b2439832c5843d72a813fa9c2ade9149e30982fe617d05e6214356e7c6d4a",
        "redactedText": "Pinned v0.26.5 evidence: `windowStatus: OBSERVATION_WINDOW_COMPLETE`, `stage chain: 6`, `value scorecard: VALUE_SCORECARD_COMPLETE`, `recommendation: HOLD_FOR_MORE_EVIDENCE`, `recommendationIsAuthority: false`, `policyDecision: null`, `reda",
        "privatePatternDetected": false,
        "decisionVerbDetected": false,
        "semanticDecisionTokenPersisted": false
      },
      {
        "index": 4,
        "rawSha256": "88dbb7d40ef8eabd8bcac8aba77fec7c6dcf3d3dee44c375bcd994ecce450351",
        "rawBytes": 290,
        "redactedSha256": "88dbb7d40ef8eabd8bcac8aba77fec7c6dcf3d3dee44c375bcd994ecce450351",
        "redactedText": "The window chains existing safe stages end-to-end: explicit repo-local multisource read evidence, positive pass, usefulness/noise scorecard, controlled operator review queue, local/manual outcome capture, and value scorecard. The scorecard ",
        "privatePatternDetected": false,
        "decisionVerbDetected": false,
        "semanticDecisionTokenPersisted": false
      },
      {
        "index": 5,
        "rawSha256": "587350ac57646d0ec6cdedd56714310ad01ed1da556fc374bb547a1c626b777c",
        "rawBytes": 22,
        "redactedSha256": "587350ac57646d0ec6cdedd56714310ad01ed1da556fc374bb547a1c626b777c",
        "redactedText": "## v0.26.5 phase close",
        "privatePatternDetected": false,
        "decisionVerbDetected": false,
        "semanticDecisionTokenPersisted": false
      }
    ],
    "reportMarkdown": "# Live Adapter Shadow-Read Report v0.19.5\n\n- Barrier crossed: local adapter shadow-read gate\n- Adapter: repo-local-file-read-adapter-v0\n- Operator-run: true; one-shot: true; local-only/read-only/passive-only: true\n- Records read: 6 / limit 6\n- Redacted evidence only: true; rawPersisted: false; rawOutput: false\n- policyDecision: null; agentConsumedOutput: false; unexpectedPermits: 0\n- Enforcement/authorization/approval/block/allow: false\n\n## Redacted evidence preview\n- #0: # Synaptic Mesh v0.26.5\n- #1: This is the public review release `v0.26.5`. Current v0.26.5 status is narrower than live runtime and crosses the next safe barrier after the v0.25 value scorecard: **passive observation window**.\n- #2: The v0.26 ladder is disabled-by-default, operator-run one-shot, local-only, passive/read-only, bounded to explicit repo-local sources and 3 queue/outcome items, local manual outcome fixtures only, redaction-before-persist, redacted evidence\n- #3: Pinned v0.26.5 evidence: `windowStatus: OBSERVATION_WINDOW_COMPLETE`, `stage chain: 6`, `value scorecard: VALUE_SCORECARD_COMPLETE`, `recommendation: HOLD_FOR_MORE_EVIDENCE`, `recommendationIsAuthority: false`, `policyDecision: null`, `reda\n- #4: The window chains existing safe stages end-to-end: explicit repo-local multisource read evidence, positive pass, usefulness/noise scorecard, controlled operator review queue, local/manual outcome capture, and value scorecard. The scorecard\n- #5: ## v0.26.5 phase close\n"
  }
}
