{
  "cases": [
    {
      "id": "useful-valid-pass-a",
      "label": "useful valid pass",
      "caseType": "useful_valid_pass",
      "expectedUsefulness": true,
      "expectedNoise": false,
      "classification": "PASS_TO_HUMAN_REVIEW",
      "positiveUtilityGatePassed": true,
      "observedPassToHumanReview": true,
      "rejectionReasons": [],
      "trueUsefulPass": true,
      "falsePass": false,
      "usefulReject": false,
      "missedUsefulPass": false,
      "noisyReject": false,
      "authorityViolations": [],
      "valueWarning": false,
      "notes": ""
    },
    {
      "id": "useful-valid-pass-b",
      "label": "second useful valid pass",
      "caseType": "useful_valid_pass",
      "expectedUsefulness": true,
      "expectedNoise": false,
      "classification": "PASS_TO_HUMAN_REVIEW",
      "positiveUtilityGatePassed": true,
      "observedPassToHumanReview": true,
      "rejectionReasons": [],
      "trueUsefulPass": true,
      "falsePass": false,
      "usefulReject": false,
      "missedUsefulPass": false,
      "noisyReject": false,
      "authorityViolations": [],
      "valueWarning": false,
      "notes": ""
    },
    {
      "id": "source-failure-allowed-explicit-threshold",
      "label": "source failure allowed only with explicit threshold",
      "caseType": "useful_source_failure_allowed_with_explicit_threshold",
      "expectedUsefulness": true,
      "expectedNoise": false,
      "classification": "PASS_TO_HUMAN_REVIEW",
      "positiveUtilityGatePassed": true,
      "observedPassToHumanReview": true,
      "rejectionReasons": [],
      "trueUsefulPass": true,
      "falsePass": false,
      "usefulReject": false,
      "missedUsefulPass": false,
      "noisyReject": false,
      "authorityViolations": [],
      "valueWarning": false,
      "notes": ""
    },
    {
      "id": "noisy-private-reject",
      "label": "noisy private-pattern reject",
      "caseType": "noisy_safe_reject",
      "expectedUsefulness": false,
      "expectedNoise": true,
      "classification": "REJECTED_NOT_READY_FOR_HUMAN_REVIEW",
      "positiveUtilityGatePassed": false,
      "observedPassToHumanReview": false,
      "rejectionReasons": [
        "private_pattern_detected_in_positive_case"
      ],
      "trueUsefulPass": false,
      "falsePass": false,
      "usefulReject": false,
      "missedUsefulPass": false,
      "noisyReject": true,
      "authorityViolations": [],
      "valueWarning": false,
      "notes": ""
    },
    {
      "id": "source-failure-default-reject",
      "label": "source failure reject by default",
      "caseType": "source_failure_reject_default",
      "expectedUsefulness": false,
      "expectedNoise": true,
      "classification": "REJECTED_NOT_READY_FOR_HUMAN_REVIEW",
      "positiveUtilityGatePassed": false,
      "observedPassToHumanReview": false,
      "rejectionReasons": [
        "source_failures_exceed_positive_gate_threshold"
      ],
      "trueUsefulPass": false,
      "falsePass": false,
      "usefulReject": false,
      "missedUsefulPass": false,
      "noisyReject": true,
      "authorityViolations": [],
      "valueWarning": false,
      "notes": ""
    },
    {
      "id": "malformed-bounds-reject",
      "label": "malformed bounds reject",
      "caseType": "malformed_reject",
      "expectedUsefulness": false,
      "expectedNoise": true,
      "classification": "REJECTED_NOT_READY_FOR_HUMAN_REVIEW",
      "positiveUtilityGatePassed": false,
      "observedPassToHumanReview": false,
      "rejectionReasons": [
        "records_per_source_exceeds_bound"
      ],
      "trueUsefulPass": false,
      "falsePass": false,
      "usefulReject": false,
      "missedUsefulPass": false,
      "noisyReject": true,
      "authorityViolations": [],
      "valueWarning": false,
      "notes": ""
    },
    {
      "id": "forbidden-alias-reject",
      "label": "forbidden alias reject",
      "caseType": "forbidden_alias_reject",
      "expectedUsefulness": false,
      "expectedNoise": true,
      "classification": "REJECTED_NOT_READY_FOR_HUMAN_REVIEW",
      "positiveUtilityGatePassed": false,
      "observedPassToHumanReview": false,
      "rejectionReasons": [
        "forbidden_summary_true:networkFetch"
      ],
      "trueUsefulPass": false,
      "falsePass": false,
      "usefulReject": false,
      "missedUsefulPass": false,
      "noisyReject": true,
      "authorityViolations": [],
      "valueWarning": false,
      "notes": ""
    },
    {
      "id": "borderline-insufficient-records-reject",
      "label": "borderline insufficient records reject",
      "caseType": "borderline_insufficient_records_reject",
      "expectedUsefulness": false,
      "expectedNoise": true,
      "classification": "REJECTED_NOT_READY_FOR_HUMAN_REVIEW",
      "positiveUtilityGatePassed": false,
      "observedPassToHumanReview": false,
      "rejectionReasons": [
        "insufficient_records_for_useful_human_review"
      ],
      "trueUsefulPass": false,
      "falsePass": false,
      "usefulReject": false,
      "missedUsefulPass": false,
      "noisyReject": true,
      "authorityViolations": [],
      "valueWarning": false,
      "notes": ""
    },
    {
      "id": "forbidden-authority-classification-reject",
      "label": "forbidden authority classification token reject",
      "caseType": "malformed_forbidden_reject",
      "expectedUsefulness": false,
      "expectedNoise": true,
      "classification": "REJECTED_NOT_READY_FOR_HUMAN_REVIEW",
      "positiveUtilityGatePassed": false,
      "observedPassToHumanReview": false,
      "rejectionReasons": [
        "forbidden_authority_classification_token"
      ],
      "trueUsefulPass": false,
      "falsePass": false,
      "usefulReject": false,
      "missedUsefulPass": false,
      "noisyReject": true,
      "authorityViolations": [],
      "valueWarning": false,
      "notes": ""
    }
  ],
  "metrics": {
    "totalCases": 9,
    "expectedUsefulCases": 3,
    "expectedNoiseCases": 6,
    "observedPasses": 3,
    "observedRejects": 6,
    "trueUsefulPasses": 3,
    "falsePasses": 0,
    "usefulRejects": 0,
    "missedUsefulPasses": 0,
    "noisyRejects": 6,
    "noiseRejected": 6,
    "falseValueWarnings": 0,
    "authorityViolations": 0,
    "passPrecision": 1,
    "passUsefulness": 1,
    "noiseRejectionRate": 1,
    "reviewBurdenEstimate": {
      "passCount": 3,
      "warningCount": 0,
      "reviewerQueueItems": 3,
      "qualitative": "low"
    }
  },
  "recommendation": "advance"
}
