{
  "readOnlyAdapterBoundaryDesignFirstPackage": "pass",
  "v040AlphaBoundarySpec": "pass",
  "v041MisuseFailureCatalog": "pass",
  "v042ReproducibilityDriftGate": "pass",
  "v043ReviewerRunbook": "pass",
  "v044SimulatedReadOnlyAdapter": "pass",
  "realAdapterAuthorized": false,
  "frameworkIntegrationAuthorized": false,
  "liveTrafficAuthorized": false,
  "toolExecution": false,
  "memoryWrite": false,
  "configWrite": false,
  "externalPublication": false,
  "approvalEmission": false,
  "machineReadablePolicyDecision": false,
  "agentConsumed": false,
  "mayBlock": false,
  "mayAllow": false,
  "enforcement": false,
  "failures": []
}
